speakeasy2/__init__.py
speakeasy2/_speakeasy2.abi3.so
speakeasy2/_speakeasy2.c
speakeasy2-0.2.0.dist-info/METADATA
speakeasy2-0.2.0.dist-info/WHEEL
speakeasy2-0.2.0.dist-info/RECORD
speakeasy2-0.2.0.dist-info/licenses/LICENSE
