Metadata-Version: 2.4
Name: speakeasy2
Version: 0.2.0
Summary: SpeakEasy2 community detection algorithm
Keywords: network,community detection,cluster,graph
Author-Email: David R Connell <david32@dcon.addy.io>
License-Expression: GPL-3.0-or-later
Project-URL: Repository, https://github.com/SpeakEasy-2/python-speakeasy2.git
Project-URL: Changelog, https://github.com/SpeakEasy-2/python-speakeasy2/blob/master/CHANGELOG.md
Project-URL: Bug Tracker, https://github.com/SpeakEasy-2/python-speakeasy2/issues
Requires-Python: >=3.10
Requires-Dist: igraph>=0.11.0
Requires-Dist: numpy>=2.0.0
